enot_autodl_yandex-3.2.0.dist-info/METADATA
enot_autodl_yandex-3.2.0.dist-info/LICENSE
enot_autodl_yandex-3.2.0.dist-info/top_level.txt
enot_autodl_yandex-3.2.0.dist-info/WHEEL
enot_autodl_yandex-3.2.0.dist-info/RECORD
enot/__init__.py
enot/VERSION
enot/autogeneration/transform_model.cpython-39-x86_64-linux-gnu.so
enot/autogeneration/search_variants_from_model.cpython-39-x86_64-linux-gnu.so
enot/autogeneration/__init__.py
enot/visualization/search.cpython-39-x86_64-linux-gnu.so
enot/visualization/__init__.py
enot/visualization/latency.cpython-39-x86_64-linux-gnu.so
enot/experimental/batch_norm_tuning.cpython-39-x86_64-linux-gnu.so
enot/experimental/__init__.py
enot/experimental/resolution_search/resolution_strategy.cpython-39-x86_64-linux-gnu.so
enot/experimental/resolution_search/__init__.py
enot/experimental/resolution_search/fixed_latency_search.cpython-39-x86_64-linux-gnu.so
enot/experimental/resolution_search/golden_section_resolution_search.cpython-39-x86_64-linux-gnu.so
enot/optimize/train.cpython-39-x86_64-linux-gnu.so
enot/optimize/search.cpython-39-x86_64-linux-gnu.so
enot/optimize/base.cpython-39-x86_64-linux-gnu.so
enot/optimize/__init__.py
enot/optimize/lagrangian_optimization.cpython-39-x86_64-linux-gnu.so
enot/optimize/utils.cpython-39-x86_64-linux-gnu.so
enot/optimize/pretrain.cpython-39-x86_64-linux-gnu.so
enot/protection/yandex_protection.cpython-39-x86_64-linux-gnu.so
enot/protection/app_token_service_pb2_grpc.cpython-39-x86_64-linux-gnu.so
enot/protection/__init__.py
enot/protection/app_token_service_pb2.cpython-39-x86_64-linux-gnu.so
enot/graph/node_rules.cpython-39-x86_64-linux-gnu.so
enot/graph/transform_params.cpython-39-x86_64-linux-gnu.so
enot/graph/custom_tracer.cpython-39-x86_64-linux-gnu.so
enot/graph/__init__.py
enot/graph/common.cpython-39-x86_64-linux-gnu.so
enot/graph/intermediate_representation.cpython-39-x86_64-linux-gnu.so
enot/graph/match_patterns/yolo.cpython-39-x86_64-linux-gnu.so
enot/graph/match_patterns/base.cpython-39-x86_64-linux-gnu.so
enot/graph/match_patterns/linear.cpython-39-x86_64-linux-gnu.so
enot/graph/match_patterns/__init__.py
enot/graph/match_patterns/resnet.cpython-39-x86_64-linux-gnu.so
