Metadata-Version: 2.1
Name: enot-autodl-yandex
Version: 3.2.0
Summary: AutoDL framework for neural network compression & acceleration
Home-page: https://enot.ai
Author: ENOT LLC
Author-email: enot@enot.ai
License: ENOT License v1.0
Keywords: AI,Neural architecture search
Classifier: License :: Other/Proprietary License
License-File: LICENSE
Requires-Dist: tblib
Requires-Dist: torch (<1.14.0,>=1.8.0)
Requires-Dist: torch-optimizer
Requires-Dist: torchvision
Requires-Dist: numpy (>=1.16.4)
Requires-Dist: pandas
Requires-Dist: scipy (>=1.2.2)
Requires-Dist: PyYAML
Requires-Dist: tqdm
Requires-Dist: tensorboard
Requires-Dist: requests
Requires-Dist: ipywidgets
Requires-Dist: pillow (>=6.2.1)
Requires-Dist: matplotlib (>=2.2.2)
Requires-Dist: thop
Requires-Dist: ptflops
Requires-Dist: pthflops
Requires-Dist: fvcore
Requires-Dist: networkx
Requires-Dist: pulp (==2.4)
Requires-Dist: tabulate
Requires-Dist: onnx
Requires-Dist: ninja
Requires-Dist: optuna
Requires-Dist: onnx2torch
Requires-Dist: grpcio (>=1.30.0)
Requires-Dist: grpcio-reflection (>=1.30.0)
Requires-Dist: google-api-core (>=1.21.0)
